resim/actor/state/proto/observable_state_pb2.py
resim/curves/proto/two_jet_pb2.py
resim/msg/detection_pb2.py
resim/msg/header_pb2.py
resim/msg/navsat_pb2.py
resim/msg/odometry_pb2.py
resim/msg/pose_pb2.py
resim/msg/primitives_pb2.py
resim/msg/transform_pb2.py
resim/transforms/proto/frame_3_pb2.py
resim/transforms/proto/framed_vector_3_pb2.py
resim/transforms/proto/se3_pb2.py
resim/transforms/proto/so3_pb2.py
resim_msg-0.0.0.dist-info/WHEEL
resim_msg-0.0.0.dist-info/METADATA
resim_msg-0.0.0.dist-info/RECORD
